abc_test_ti_client/__init__.py
abc_test_ti_client/api_client.py
abc_test_ti_client/api_response.py
abc_test_ti_client/configuration.py
abc_test_ti_client/exceptions.py
abc_test_ti_client/py.typed
abc_test_ti_client/rest.py
abc_test_ti_client/api/__init__.py
abc_test_ti_client/api/pet_api.py
abc_test_ti_client/api/store_api.py
abc_test_ti_client/api/user_api.py
abc_test_ti_client/models/__init__.py
abc_test_ti_client/models/address.py
abc_test_ti_client/models/api_response.py
abc_test_ti_client/models/category.py
abc_test_ti_client/models/customer.py
abc_test_ti_client/models/order.py
abc_test_ti_client/models/pet.py
abc_test_ti_client/models/tag.py
abc_test_ti_client/models/user.py
abc_test_ti_client-1.0.0.dist-info/METADATA
abc_test_ti_client-1.0.0.dist-info/WHEEL
abc_test_ti_client-1.0.0.dist-info/top_level.txt
abc_test_ti_client-1.0.0.dist-info/RECORD
